{
  "summary": {
    "requested_rps": 10.5,
    "duration_seconds": 60,
    "wall_clock_seconds": 62.4670623819984,
    "total_requests": 630,
    "achieved_rps": 10.085314980035811,
    "ok": 630,
    "timeouts": 0,
    "http_errors": 0,
    "client_errors": 0,
    "latency_p50": 1.055075153009966,
    "latency_p95": 4.067460556994774,
    "latency_p99": 5.434212544001639,
    "latency_max": 7.20457338799315,
    "avg_iterations": 1.0
  },
  "results": [
    {
      "latency_seconds": 0.42523654000251554,
      "status": "ok",
      "error": null,
      "agent_ok": true,
      "iterations": 1
    },
    {
      "latency_seconds": 0.22103333999984898,
      "status": "ok",
      "error": null,
      "agent_ok": true,
      "iterations": 1
    },
    {
      "latency_seconds": 0.9973498779872898,
      "status": "ok",
      "error": null,
      "agent_ok": true,
      "iterations": 1
    },
    {
      "latency_seconds": 0.8559105729946168,
      "status": "ok",
      "error": null,
      "agent_ok": true,
      "iterations": 1
    },
    {
      "latency_seconds": 0.32983247500669677,
      "status": "ok",
      "error": null,
      "agent_ok": true,
      "iterations": 1
    },
    {
      "latency_seconds": 0.8109424459980801,
      "status": "ok",
      "error": null,
      "agent_ok": true,
      "iterations": 1
    },
    {
      "latency_seconds": 0.3780571700044675,
      "status": "ok",
      "error": null,
      "agent_ok": true,
      "iterations": 1
    },
    {
      "latency_seconds": 1.2316866879991721,
      "status": "ok",
      "error": null,
      "agent_ok": true,
      "iterations": 1
    },
    {
      "latency_seconds": 1.0014398769999389,
      "status": "ok",
      "error": null,
      "agent_ok": true,
      "iterations": 1
    },
    {
      "latency_seconds": 0.7301588990085293,
      "status": "ok",
      "error": null,
      "agent_ok": true,
      "iterations": 1
    },
    {
      "latency_seconds": 1.7873450619954383,
      "status": "ok",
      "error": null,
      "agent_ok": true,
      "iterations": 1
    },
    {
      "latency_seconds": 0.4972989090019837,
      "status": "ok",
      "error": null,
      "agent_ok": true,
      "iterations": 1
    },
    {
      "latency_seconds": 1.6406866470060777,
      "status": "ok",
      "error": null,
      "agent_ok": true,
      "iterations": 1
    },
    {
      "latency_seconds": 0.9858045120054157,
      "status": "ok",
      "error": null,
      "agent_ok": true,
      "iterations": 1
    },
    {
      "latency_seconds": 1.4727704500110121,
      "status": "ok",
      "error": null,
      "agent_ok": true,
      "iterations": 1
    },
    {
      "latency_seconds": 0.9098477990046376,
      "status": "ok",
      "error": null,
      "agent_ok": true,
      "iterations": 1
    },
    {
      "latency_seconds": 0.624178320998908,
      "status": "ok",
      "error": null,
      "agent_ok": true,
      "iterations": 1
    },
    {
      "latency_seconds": 0.7623732270003529,
      "status": "ok",
      "error": null,
      "agent_ok": true,
      "iterations": 1
    },
    {
      "latency_seconds": 1.2210126819991274,
      "status": "ok",
      "error": null,
      "agent_ok": true,
      "iterations": 1
    },
    {
      "latency_seconds": 0.566605776999495,
      "status": "ok",
      "error": null,
      "agent_ok": true,
      "iterations": 1
    },
    {
      "latency_seconds": 0.7201317490107613,
      "status": "ok",
      "error": null,
      "agent_ok": false,
      "iterations": 1
    },
    {
      "latency_seconds": 0.7263768330012681,
      "status": "ok",
      "error": null,
      "agent_ok": true,
      "iterations": 1
    },
    {
      "latency_seconds": 1.3566248349961825,
      "status": "ok",
      "error": null,
      "agent_ok": false,
      "iterations": 1
    },
    {
      "latency_seconds": 1.246921536992886,
      "status": "ok",
      "error": null,
      "agent_ok": true,
      "iterations": 1
    },
    {
      "latency_seconds": 0.6794404740066966,
      "status": "ok",
      "error": null,
      "agent_ok": true,
      "iterations": 1
    },
    {
      "latency_seconds": 0.7749964639951941,
      "status": "ok",
      "error": null,
      "agent_ok": true,
      "iterations": 1
    },
    {
      "latency_seconds": 2.012241770993569,
      "status": "ok",
      "error": null,
      "agent_ok": true,
      "iterations": 1
    },
    {
      "latency_seconds": 0.7126150319963926,
      "status": "ok",
      "error": null,
      "agent_ok": true,
      "iterations": 1
    },
    {
      "latency_seconds": 1.1077584470040165,
      "status": "ok",
      "error": null,
      "agent_ok": true,
      "iterations": 1
    },
    {
      "latency_seconds": 1.4169680190098006,
      "status": "ok",
      "error": null,
      "agent_ok": true,
      "iterations": 1
    },
    {
      "latency_seconds": 1.5517238350003026,
      "status": "ok",
      "error": null,
      "agent_ok": true,
      "iterations": 1
    },
    {
      "latency_seconds": 0.6015291980002075,
      "status": "ok",
      "error": null,
      "agent_ok": true,
      "iterations": 1
    },
    {
      "latency_seconds": 0.8239153899921803,
      "status": "ok",
      "error": null,
      "agent_ok": true,
      "iterations": 1
    },
    {
      "latency_seconds": 3.8325496509933146,
      "status": "ok",
      "error": null,
      "agent_ok": true,
      "iterations": 1
    },
    {
      "latency_seconds": 0.26353132000076585,
      "status": "ok",
      "error": null,
      "agent_ok": true,
      "iterations": 1
    },
    {
      "latency_seconds": 0.6258245219942182,
      "status": "ok",
      "error": null,
      "agent_ok": true,
      "iterations": 1
    },
    {
      "latency_seconds": 0.46709709698916413,
      "status": "ok",
      "error": null,
      "agent_ok": true,
      "iterations": 1
    },
    {
      "latency_seconds": 0.8474732610047795,
      "status": "ok",
      "error": null,
      "agent_ok": true,
      "iterations": 1
    },
    {
      "latency_seconds": 1.9332431749935495,
      "status": "ok",
      "error": null,
      "agent_ok": true,
      "iterations": 1
    },
    {
      "latency_seconds": 1.095470761996694,
      "status": "ok",
      "error": null,
      "agent_ok": false,
      "iterations": 1
    },
    {
      "latency_seconds": 0.7036988339968957,
      "status": "ok",
      "error": null,
      "agent_ok": true,
      "iterations": 1
    },
    {
      "latency_seconds": 0.6476363679976203,
      "status": "ok",
      "error": null,
      "agent_ok": true,
      "iterations": 1
    },
    {
      "latency_seconds": 0.6302952149999328,
      "status": "ok",
      "error": null,
      "agent_ok": false,
      "iterations": 1
    },
    {
      "latency_seconds": 1.6316069090098608,
      "status": "ok",
      "error": null,
      "agent_ok": true,
      "iterations": 1
    },
    {
      "latency_seconds": 0.992133712003124,
      "status": "ok",
      "error": null,
      "agent_ok": true,
      "iterations": 1
    },
    {
      "latency_seconds": 0.9156448540015845,
      "status": "ok",
      "error": null,
      "agent_ok": true,
      "iterations": 1
    },
    {
      "latency_seconds": 0.8637188440043246,
      "status": "ok",
      "error": null,
      "agent_ok": true,
      "iterations": 1
    },
    {
      "latency_seconds": 0.7031612550053978,
      "status": "ok",
      "error": null,
      "agent_ok": true,
      "iterations": 1
    },
    {
      "latency_seconds": 3.086733855001512,
      "status": "ok",
      "error": null,
      "agent_ok": true,
      "iterations": 1
    },
    {
      "latency_seconds": 1.6083151920029195,
      "status": "ok",
      "error": null,
      "agent_ok": true,
      "iterations": 1
    },
    {
      "latency_seconds": 3.2707232879911317,
      "status": "ok",
      "error": null,
      "agent_ok": true,
      "iterations": 1
    },
    {
      "latency_seconds": 1.4133561589987949,
      "status": "ok",
      "error": null,
      "agent_ok": true,
      "iterations": 1
    },
    {
      "latency_seconds": 0.6480715140060056,
      "status": "ok",
      "error": null,
      "agent_ok": true,
      "iterations": 1
    },
    {
      "latency_seconds": 1.8385274569882313,
      "status": "ok",
      "error": null,
      "agent_ok": true,
      "iterations": 1
    },
    {
      "latency_seconds": 1.3250323429965647,
      "status": "ok",
      "error": null,
      "agent_ok": true,
      "iterations": 1
    },
    {
      "latency_seconds": 1.4704276620032033,
      "status": "ok",
      "error": null,
      "agent_ok": true,
      "iterations": 1
    },
    {
      "latency_seconds": 4.247147859001416,
      "status": "ok",
      "error": null,
      "agent_ok": true,
      "iterations": 1
    },
    {
      "latency_seconds": 1.0116185609949753,
      "status": "ok",
      "error": null,
      "agent_ok": true,
      "iterations": 1
    },
    {
      "latency_seconds": 1.4547470649995375,
      "status": "ok",
      "error": null,
      "agent_ok": true,
      "iterations": 1
    },
    {
      "latency_seconds": 1.0181458690058207,
      "status": "ok",
      "error": null,
      "agent_ok": true,
      "iterations": 1
    },
    {
      "latency_seconds": 0.5890599260019371,
      "status": "ok",
      "error": null,
      "agent_ok": true,
      "iterations": 1
    },
    {
      "latency_seconds": 1.112549322002451,
      "status": "ok",
      "error": null,
      "agent_ok": false,
      "iterations": 1
    },
    {
      "latency_seconds": 1.0241397359932307,
      "status": "ok",
      "error": null,
      "agent_ok": true,
      "iterations": 1
    },
    {
      "latency_seconds": 1.529991424002219,
      "status": "ok",
      "error": null,
      "agent_ok": true,
      "iterations": 1
    },
    {
      "latency_seconds": 1.667196779002552,
      "status": "ok",
      "error": null,
      "agent_ok": true,
      "iterations": 1
    },
    {
      "latency_seconds": 0.48551034700358286,
      "status": "ok",
      "error": null,
      "agent_ok": true,
      "iterations": 1
    },
    {
      "latency_seconds": 1.3558535269985441,
      "status": "ok",
      "error": null,
      "agent_ok": true,
      "iterations": 1
    },
    {
      "latency_seconds": 1.260768273001304,
      "status": "ok",
      "error": null,
      "agent_ok": true,
      "iterations": 1
    },
    {
      "latency_seconds": 2.8229195780004375,
      "status": "ok",
      "error": null,
      "agent_ok": true,
      "iterations": 1
    },
    {
      "latency_seconds": 1.040459201001795,
      "status": "ok",
      "error": null,
      "agent_ok": true,
      "iterations": 1
    },
    {
      "latency_seconds": 3.0041443060035817,
      "status": "ok",
      "error": null,
      "agent_ok": true,
      "iterations": 1
    },
    {
      "latency_seconds": 0.7877131019922672,
      "status": "ok",
      "error": null,
      "agent_ok": true,
      "iterations": 1
    },
    {
      "latency_seconds": 0.9904943680012366,
      "status": "ok",
      "error": null,
      "agent_ok": true,
      "iterations": 1
    },
    {
      "latency_seconds": 0.5496264579996932,
      "status": "ok",
      "error": null,
      "agent_ok": true,
      "iterations": 1
    },
    {
      "latency_seconds": 1.3119298470119247,
      "status": "ok",
      "error": null,
      "agent_ok": true,
      "iterations": 1
    },
    {
      "latency_seconds": 5.427106479008216,
      "status": "ok",
      "error": null,
      "agent_ok": true,
      "iterations": 1
    },
    {
      "latency_seconds": 2.7610549720120616,
      "status": "ok",
      "error": null,
      "agent_ok": true,
      "iterations": 1
    },
    {
      "latency_seconds": 4.308925673991325,
      "status": "ok",
      "error": null,
      "agent_ok": true,
      "iterations": 1
    },
    {
      "latency_seconds": 0.911939223005902,
      "status": "ok",
      "error": null,
      "agent_ok": true,
      "iterations": 1
    },
    {
      "latency_seconds": 1.4799577990052057,
      "status": "ok",
      "error": null,
      "agent_ok": true,
      "iterations": 1
    },
    {
      "latency_seconds": 1.1362233659892809,
      "status": "ok",
      "error": null,
      "agent_ok": true,
      "iterations": 1
    },
    {
      "latency_seconds": 4.408958166008233,
      "status": "ok",
      "error": null,
      "agent_ok": true,
      "iterations": 1
    },
    {
      "latency_seconds": 1.1449592370045139,
      "status": "ok",
      "error": null,
      "agent_ok": true,
      "iterations": 1
    },
    {
      "latency_seconds": 0.8864673289936036,
      "status": "ok",
      "error": null,
      "agent_ok": true,
      "iterations": 1
    },
    {
      "latency_seconds": 5.198393337006564,
      "status": "ok",
      "error": null,
      "agent_ok": true,
      "iterations": 1
    },
    {
      "latency_seconds": 3.944254734000424,
      "status": "ok",
      "error": null,
      "agent_ok": true,
      "iterations": 1
    },
    {
      "latency_seconds": 1.3324206179968314,
      "status": "ok",
      "error": null,
      "agent_ok": true,
      "iterations": 1
    },
    {
      "latency_seconds": 1.2514646269992227,
      "status": "ok",
      "error": null,
      "agent_ok": true,
      "iterations": 1
    },
    {
      "latency_seconds": 0.8351556620036718,
      "status": "ok",
      "error": null,
      "agent_ok": true,
      "iterations": 1
    },
    {
      "latency_seconds": 0.6579358699964359,
      "status": "ok",
      "error": null,
      "agent_ok": true,
      "iterations": 1
    },
    {
      "latency_seconds": 0.8658409549971111,
      "status": "ok",
      "error": null,
      "agent_ok": true,
      "iterations": 1
    },
    {
      "latency_seconds": 0.3345858730026521,
      "status": "ok",
      "error": null,
      "agent_ok": true,
      "iterations": 1
    },
    {
      "latency_seconds": 1.315520321004442,
      "status": "ok",
      "error": null,
      "agent_ok": true,
      "iterations": 1
    },
    {
      "latency_seconds": 1.4969019999989541,
      "status": "ok",
      "error": null,
      "agent_ok": true,
      "iterations": 1
    },
    {
      "latency_seconds": 2.140941407007631,
      "status": "ok",
      "error": null,
      "agent_ok": true,
      "iterations": 1
    },
    {
      "latency_seconds": 0.823373363004066,
      "status": "ok",
      "error": null,
      "agent_ok": true,
      "iterations": 1
    },
    {
      "latency_seconds": 1.5191608269960852,
      "status": "ok",
      "error": null,
      "agent_ok": true,
      "iterations": 1
    },
    {
      "latency_seconds": 0.5742695460066898,
      "status": "ok",
      "error": null,
      "agent_ok": true,
      "iterations": 1
    },
    {
      "latency_seconds": 0.9798279820097378,
      "status": "ok",
      "error": null,
      "agent_ok": true,
      "iterations": 1
    },
    {
      "latency_seconds": 1.1920098520058673,
      "status": "ok",
      "error": null,
      "agent_ok": true,
      "iterations": 1
    },
    {
      "latency_seconds": 1.2369378750008764,
      "status": "ok",
      "error": null,
      "agent_ok": true,
      "iterations": 1
    },
    {
      "latency_seconds": 1.546479836004437,
      "status": "ok",
      "error": null,
      "agent_ok": true,
      "iterations": 1
    },
    {
      "latency_seconds": 0.7204832989955321,
      "status": "ok",
      "error": null,
      "agent_ok": false,
      "iterations": 1
    },
    {
      "latency_seconds": 1.0289141950051999,
      "status": "ok",
      "error": null,
      "agent_ok": true,
      "iterations": 1
    },
    {
      "latency_seconds": 0.8176622219907586,
      "status": "ok",
      "error": null,
      "agent_ok": true,
      "iterations": 1
    },
    {
      "latency_seconds": 3.7479578320053406,
      "status": "ok",
      "error": null,
      "agent_ok": true,
      "iterations": 1
    },
    {
      "latency_seconds": 1.3909732289903332,
      "status": "ok",
      "error": null,
      "agent_ok": true,
      "iterations": 1
    },
    {
      "latency_seconds": 0.7267511960089905,
      "status": "ok",
      "error": null,
      "agent_ok": true,
      "iterations": 1
    },
    {
      "latency_seconds": 0.541004642000189,
      "status": "ok",
      "error": null,
      "agent_ok": true,
      "iterations": 1
    },
    {
      "latency_seconds": 0.604007467001793,
      "status": "ok",
      "error": null,
      "agent_ok": false,
      "iterations": 1
    },
    {
      "latency_seconds": 1.383764432001044,
      "status": "ok",
      "error": null,
      "agent_ok": true,
      "iterations": 1
    },
    {
      "latency_seconds": 1.5977118489972781,
      "status": "ok",
      "error": null,
      "agent_ok": true,
      "iterations": 1
    },
    {
      "latency_seconds": 1.332462817998021,
      "status": "ok",
      "error": null,
      "agent_ok": true,
      "iterations": 1
    },
    {
      "latency_seconds": 1.2895546830113744,
      "status": "ok",
      "error": null,
      "agent_ok": true,
      "iterations": 1
    },
    {
      "latency_seconds": 1.1513247780094389,
      "status": "ok",
      "error": null,
      "agent_ok": true,
      "iterations": 1
    },
    {
      "latency_seconds": 0.3074332949909149,
      "status": "ok",
      "error": null,
      "agent_ok": true,
      "iterations": 1
    },
    {
      "latency_seconds": 0.9671985330060124,
      "status": "ok",
      "error": null,
      "agent_ok": true,
      "iterations": 1
    },
    {
      "latency_seconds": 1.1144004840025445,
      "status": "ok",
      "error": null,
      "agent_ok": true,
      "iterations": 1
    },
    {
      "latency_seconds": 0.500789566009189,
      "status": "ok",
      "error": null,
      "agent_ok": true,
      "iterations": 1
    },
    {
      "latency_seconds": 1.006556812004419,
      "status": "ok",
      "error": null,
      "agent_ok": true,
      "iterations": 1
    },
    {
      "latency_seconds": 0.9178203729970846,
      "status": "ok",
      "error": null,
      "agent_ok": true,
      "iterations": 1
    },
    {
      "latency_seconds": 1.0446625759941526,
      "status": "ok",
      "error": null,
      "agent_ok": true,
      "iterations": 1
    },
    {
      "latency_seconds": 1.535689836993697,
      "status": "ok",
      "error": null,
      "agent_ok": true,
      "iterations": 1
    },
    {
      "latency_seconds": 2.0472103219944984,
      "status": "ok",
      "error": null,
      "agent_ok": true,
      "iterations": 1
    },
    {
      "latency_seconds": 1.0084505139966495,
      "status": "ok",
      "error": null,
      "agent_ok": true,
      "iterations": 1
    },
    {
      "latency_seconds": 1.0106994889938505,
      "status": "ok",
      "error": null,
      "agent_ok": true,
      "iterations": 1
    },
    {
      "latency_seconds": 0.7756585929892026,
      "status": "ok",
      "error": null,
      "agent_ok": true,
      "iterations": 1
    },
    {
      "latency_seconds": 0.5585458809946431,
      "status": "ok",
      "error": null,
      "agent_ok": true,
      "iterations": 1
    },
    {
      "latency_seconds": 0.8443419969989918,
      "status": "ok",
      "error": null,
      "agent_ok": true,
      "iterations": 1
    },
    {
      "latency_seconds": 0.6370405649940949,
      "status": "ok",
      "error": null,
      "agent_ok": true,
      "iterations": 1
    },
    {
      "latency_seconds": 3.490198429004522,
      "status": "ok",
      "error": null,
      "agent_ok": true,
      "iterations": 1
    },
    {
      "latency_seconds": 1.142688273001113,
      "status": "ok",
      "error": null,
      "agent_ok": true,
      "iterations": 1
    },
    {
      "latency_seconds": 0.4985804639873095,
      "status": "ok",
      "error": null,
      "agent_ok": true,
      "iterations": 1
    },
    {
      "latency_seconds": 1.0049007159977918,
      "status": "ok",
      "error": null,
      "agent_ok": true,
      "iterations": 1
    },
    {
      "latency_seconds": 1.7087927630054764,
      "status": "ok",
      "error": null,
      "agent_ok": true,
      "iterations": 1
    },
    {
      "latency_seconds": 1.1621141319919843,
      "status": "ok",
      "error": null,
      "agent_ok": true,
      "iterations": 1
    },
    {
      "latency_seconds": 1.183411863996298,
      "status": "ok",
      "error": null,
      "agent_ok": true,
      "iterations": 1
    },
    {
      "latency_seconds": 1.2867327020067023,
      "status": "ok",
      "error": null,
      "agent_ok": true,
      "iterations": 1
    },
    {
      "latency_seconds": 1.0438467539934209,
      "status": "ok",
      "error": null,
      "agent_ok": true,
      "iterations": 1
    },
    {
      "latency_seconds": 0.5685745109949494,
      "status": "ok",
      "error": null,
      "agent_ok": true,
      "iterations": 1
    },
    {
      "latency_seconds": 1.3429705000016838,
      "status": "ok",
      "error": null,
      "agent_ok": true,
      "iterations": 1
    },
    {
      "latency_seconds": 0.5146728670079028,
      "status": "ok",
      "error": null,
      "agent_ok": true,
      "iterations": 1
    },
    {
      "latency_seconds": 2.7431046099954983,
      "status": "ok",
      "error": null,
      "agent_ok": true,
      "iterations": 1
    },
    {
      "latency_seconds": 5.151767579998705,
      "status": "ok",
      "error": null,
      "agent_ok": true,
      "iterations": 1
    },
    {
      "latency_seconds": 2.169076056990889,
      "status": "ok",
      "error": null,
      "agent_ok": true,
      "iterations": 1
    },
    {
      "latency_seconds": 1.2342718290019548,
      "status": "ok",
      "error": null,
      "agent_ok": true,
      "iterations": 1
    },
    {
      "latency_seconds": 0.2725988539896207,
      "status": "ok",
      "error": null,
      "agent_ok": true,
      "iterations": 1
    },
    {
      "latency_seconds": 1.2418282300059218,
      "status": "ok",
      "error": null,
      "agent_ok": true,
      "iterations": 1
    },
    {
      "latency_seconds": 0.7901400279952213,
      "status": "ok",
      "error": null,
      "agent_ok": true,
      "iterations": 1
    },
    {
      "latency_seconds": 2.079552509007044,
      "status": "ok",
      "error": null,
      "agent_ok": true,
      "iterations": 1
    },
    {
      "latency_seconds": 0.7915552339982241,
      "status": "ok",
      "error": null,
      "agent_ok": true,
      "iterations": 1
    },
    {
      "latency_seconds": 2.219472359007341,
      "status": "ok",
      "error": null,
      "agent_ok": true,
      "iterations": 1
    },
    {
      "latency_seconds": 1.3744334820075892,
      "status": "ok",
      "error": null,
      "agent_ok": true,
      "iterations": 1
    },
    {
      "latency_seconds": 1.3033144799992442,
      "status": "ok",
      "error": null,
      "agent_ok": true,
      "iterations": 1
    },
    {
      "latency_seconds": 0.3702987800061237,
      "status": "ok",
      "error": null,
      "agent_ok": true,
      "iterations": 1
    },
    {
      "latency_seconds": 0.8415853640035493,
      "status": "ok",
      "error": null,
      "agent_ok": true,
      "iterations": 1
    },
    {
      "latency_seconds": 4.123791398989852,
      "status": "ok",
      "error": null,
      "agent_ok": true,
      "iterations": 1
    },
    {
      "latency_seconds": 1.0770791070099222,
      "status": "ok",
      "error": null,
      "agent_ok": true,
      "iterations": 1
    },
    {
      "latency_seconds": 2.207827598991571,
      "status": "ok",
      "error": null,
      "agent_ok": true,
      "iterations": 1
    },
    {
      "latency_seconds": 1.4545591739879455,
      "status": "ok",
      "error": null,
      "agent_ok": true,
      "iterations": 1
    },
    {
      "latency_seconds": 1.6628482969972538,
      "status": "ok",
      "error": null,
      "agent_ok": false,
      "iterations": 1
    },
    {
      "latency_seconds": 2.7094817890028935,
      "status": "ok",
      "error": null,
      "agent_ok": true,
      "iterations": 1
    },
    {
      "latency_seconds": 0.9681063979951432,
      "status": "ok",
      "error": null,
      "agent_ok": true,
      "iterations": 1
    },
    {
      "latency_seconds": 0.9314312789938413,
      "status": "ok",
      "error": null,
      "agent_ok": true,
      "iterations": 1
    },
    {
      "latency_seconds": 3.5576719570090063,
      "status": "ok",
      "error": null,
      "agent_ok": true,
      "iterations": 1
    },
    {
      "latency_seconds": 1.1921936849976191,
      "status": "ok",
      "error": null,
      "agent_ok": true,
      "iterations": 1
    },
    {
      "latency_seconds": 2.6248091320012463,
      "status": "ok",
      "error": null,
      "agent_ok": true,
      "iterations": 1
    },
    {
      "latency_seconds": 1.8132067129918141,
      "status": "ok",
      "error": null,
      "agent_ok": true,
      "iterations": 1
    },
    {
      "latency_seconds": 1.4920059729920467,
      "status": "ok",
      "error": null,
      "agent_ok": true,
      "iterations": 1
    },
    {
      "latency_seconds": 1.0612268269906053,
      "status": "ok",
      "error": null,
      "agent_ok": true,
      "iterations": 1
    },
    {
      "latency_seconds": 1.0591908040078124,
      "status": "ok",
      "error": null,
      "agent_ok": true,
      "iterations": 1
    },
    {
      "latency_seconds": 1.137420908009517,
      "status": "ok",
      "error": null,
      "agent_ok": true,
      "iterations": 1
    },
    {
      "latency_seconds": 0.9325443359994097,
      "status": "ok",
      "error": null,
      "agent_ok": true,
      "iterations": 1
    },
    {
      "latency_seconds": 0.6728441100131022,
      "status": "ok",
      "error": null,
      "agent_ok": true,
      "iterations": 1
    },
    {
      "latency_seconds": 0.6275378720019944,
      "status": "ok",
      "error": null,
      "agent_ok": true,
      "iterations": 1
    },
    {
      "latency_seconds": 2.5245496760035167,
      "status": "ok",
      "error": null,
      "agent_ok": true,
      "iterations": 1
    },
    {
      "latency_seconds": 1.2493386660062242,
      "status": "ok",
      "error": null,
      "agent_ok": false,
      "iterations": 1
    },
    {
      "latency_seconds": 0.32597634400008246,
      "status": "ok",
      "error": null,
      "agent_ok": true,
      "iterations": 1
    },
    {
      "latency_seconds": 0.9026449539960595,
      "status": "ok",
      "error": null,
      "agent_ok": true,
      "iterations": 1
    },
    {
      "latency_seconds": 1.460719431997859,
      "status": "ok",
      "error": null,
      "agent_ok": true,
      "iterations": 1
    },
    {
      "latency_seconds": 1.672065623002709,
      "status": "ok",
      "error": null,
      "agent_ok": true,
      "iterations": 1
    },
    {
      "latency_seconds": 1.081187656003749,
      "status": "ok",
      "error": null,
      "agent_ok": true,
      "iterations": 1
    },
    {
      "latency_seconds": 1.0072011620068224,
      "status": "ok",
      "error": null,
      "agent_ok": true,
      "iterations": 1
    },
    {
      "latency_seconds": 2.2263092060020426,
      "status": "ok",
      "error": null,
      "agent_ok": true,
      "iterations": 1
    },
    {
      "latency_seconds": 1.0514609100064263,
      "status": "ok",
      "error": null,
      "agent_ok": true,
      "iterations": 1
    },
    {
      "latency_seconds": 2.5141132680000737,
      "status": "ok",
      "error": null,
      "agent_ok": true,
      "iterations": 1
    },
    {
      "latency_seconds": 0.8289047440048307,
      "status": "ok",
      "error": null,
      "agent_ok": true,
      "iterations": 1
    },
    {
      "latency_seconds": 0.4623367999884067,
      "status": "ok",
      "error": null,
      "agent_ok": true,
      "iterations": 1
    },
    {
      "latency_seconds": 0.6539355160057312,
      "status": "ok",
      "error": null,
      "agent_ok": true,
      "iterations": 1
    },
    {
      "latency_seconds": 0.7513228919997346,
      "status": "ok",
      "error": null,
      "agent_ok": true,
      "iterations": 1
    },
    {
      "latency_seconds": 1.7135965219931677,
      "status": "ok",
      "error": null,
      "agent_ok": true,
      "iterations": 1
    },
    {
      "latency_seconds": 1.0554819909884827,
      "status": "ok",
      "error": null,
      "agent_ok": true,
      "iterations": 1
    },
    {
      "latency_seconds": 0.7329841939936159,
      "status": "ok",
      "error": null,
      "agent_ok": true,
      "iterations": 1
    },
    {
      "latency_seconds": 4.666328855004394,
      "status": "ok",
      "error": null,
      "agent_ok": false,
      "iterations": 1
    },
    {
      "latency_seconds": 1.4560186580056325,
      "status": "ok",
      "error": null,
      "agent_ok": true,
      "iterations": 1
    },
    {
      "latency_seconds": 0.5065036400046665,
      "status": "ok",
      "error": null,
      "agent_ok": true,
      "iterations": 1
    },
    {
      "latency_seconds": 0.8230284599994775,
      "status": "ok",
      "error": null,
      "agent_ok": true,
      "iterations": 1
    },
    {
      "latency_seconds": 0.48377740499563515,
      "status": "ok",
      "error": null,
      "agent_ok": true,
      "iterations": 1
    },
    {
      "latency_seconds": 0.6184578909887932,
      "status": "ok",
      "error": null,
      "agent_ok": true,
      "iterations": 1
    },
    {
      "latency_seconds": 0.28586953299236484,
      "status": "ok",
      "error": null,
      "agent_ok": true,
      "iterations": 1
    },
    {
      "latency_seconds": 1.3642078100092476,
      "status": "ok",
      "error": null,
      "agent_ok": true,
      "iterations": 1
    },
    {
      "latency_seconds": 1.0520480980048887,
      "status": "ok",
      "error": null,
      "agent_ok": true,
      "iterations": 1
    },
    {
      "latency_seconds": 1.5411802000016905,
      "status": "ok",
      "error": null,
      "agent_ok": false,
      "iterations": 1
    },
    {
      "latency_seconds": 0.49717044799763244,
      "status": "ok",
      "error": null,
      "agent_ok": true,
      "iterations": 1
    },
    {
      "latency_seconds": 1.3685677140019834,
      "status": "ok",
      "error": null,
      "agent_ok": true,
      "iterations": 1
    },
    {
      "latency_seconds": 0.8085919199947966,
      "status": "ok",
      "error": null,
      "agent_ok": true,
      "iterations": 1
    },
    {
      "latency_seconds": 0.9454338009963976,
      "status": "ok",
      "error": null,
      "agent_ok": true,
      "iterations": 1
    },
    {
      "latency_seconds": 0.635560524999164,
      "status": "ok",
      "error": null,
      "agent_ok": true,
      "iterations": 1
    },
    {
      "latency_seconds": 1.3332037429936463,
      "status": "ok",
      "error": null,
      "agent_ok": true,
      "iterations": 1
    },
    {
      "latency_seconds": 0.6692802250036038,
      "status": "ok",
      "error": null,
      "agent_ok": true,
      "iterations": 1
    },
    {
      "latency_seconds": 0.4887103310029488,
      "status": "ok",
      "error": null,
      "agent_ok": true,
      "iterations": 1
    },
    {
      "latency_seconds": 0.8911078160017496,
      "status": "ok",
      "error": null,
      "agent_ok": true,
      "iterations": 1
    },
    {
      "latency_seconds": 0.5215964499948313,
      "status": "ok",
      "error": null,
      "agent_ok": true,
      "iterations": 1
    },
    {
      "latency_seconds": 0.6866083869972499,
      "status": "ok",
      "error": null,
      "agent_ok": true,
      "iterations": 1
    },
    {
      "latency_seconds": 2.0449775279994356,
      "status": "ok",
      "error": null,
      "agent_ok": true,
      "iterations": 1
    },
    {
      "latency_seconds": 1.4771013319987105,
      "status": "ok",
      "error": null,
      "agent_ok": true,
      "iterations": 1
    },
    {
      "latency_seconds": 4.997859117996995,
      "status": "ok",
      "error": null,
      "agent_ok": true,
      "iterations": 1
    },
    {
      "latency_seconds": 0.7433779270068044,
      "status": "ok",
      "error": null,
      "agent_ok": true,
      "iterations": 1
    },
    {
      "latency_seconds": 1.0073273119924124,
      "status": "ok",
      "error": null,
      "agent_ok": true,
      "iterations": 1
    },
    {
      "latency_seconds": 0.6624858499999391,
      "status": "ok",
      "error": null,
      "agent_ok": true,
      "iterations": 1
    },
    {
      "latency_seconds": 0.8682967829954578,
      "status": "ok",
      "error": null,
      "agent_ok": true,
      "iterations": 1
    },
    {
      "latency_seconds": 0.8648516350076534,
      "status": "ok",
      "error": null,
      "agent_ok": true,
      "iterations": 1
    },
    {
      "latency_seconds": 0.6822104679886252,
      "status": "ok",
      "error": null,
      "agent_ok": true,
      "iterations": 1
    },
    {
      "latency_seconds": 0.5522605970036238,
      "status": "ok",
      "error": null,
      "agent_ok": true,
      "iterations": 1
    },
    {
      "latency_seconds": 0.5334306160075357,
      "status": "ok",
      "error": null,
      "agent_ok": true,
      "iterations": 1
    },
    {
      "latency_seconds": 1.299595902004512,
      "status": "ok",
      "error": null,
      "agent_ok": true,
      "iterations": 1
    },
    {
      "latency_seconds": 1.9219758070103126,
      "status": "ok",
      "error": null,
      "agent_ok": true,
      "iterations": 1
    },
    {
      "latency_seconds": 6.02664580498822,
      "status": "ok",
      "error": null,
      "agent_ok": false,
      "iterations": 1
    },
    {
      "latency_seconds": 1.4737405350024346,
      "status": "ok",
      "error": null,
      "agent_ok": true,
      "iterations": 1
    },
    {
      "latency_seconds": 0.8509696039982373,
      "status": "ok",
      "error": null,
      "agent_ok": true,
      "iterations": 1
    },
    {
      "latency_seconds": 1.0142626949964324,
      "status": "ok",
      "error": null,
      "agent_ok": true,
      "iterations": 1
    },
    {
      "latency_seconds": 0.8719202889915323,
      "status": "ok",
      "error": null,
      "agent_ok": true,
      "iterations": 1
    },
    {
      "latency_seconds": 0.6938980980048655,
      "status": "ok",
      "error": null,
      "agent_ok": true,
      "iterations": 1
    },
    {
      "latency_seconds": 0.8638965290010674,
      "status": "ok",
      "error": null,
      "agent_ok": true,
      "iterations": 1
    },
    {
      "latency_seconds": 0.6857601439987775,
      "status": "ok",
      "error": null,
      "agent_ok": true,
      "iterations": 1
    },
    {
      "latency_seconds": 0.6188747929991223,
      "status": "ok",
      "error": null,
      "agent_ok": true,
      "iterations": 1
    },
    {
      "latency_seconds": 1.1387921490095323,
      "status": "ok",
      "error": null,
      "agent_ok": true,
      "iterations": 1
    },
    {
      "latency_seconds": 0.8977550510026049,
      "status": "ok",
      "error": null,
      "agent_ok": true,
      "iterations": 1
    },
    {
      "latency_seconds": 2.2439921030018013,
      "status": "ok",
      "error": null,
      "agent_ok": false,
      "iterations": 1
    },
    {
      "latency_seconds": 1.355395418999251,
      "status": "ok",
      "error": null,
      "agent_ok": true,
      "iterations": 1
    },
    {
      "latency_seconds": 2.110709240005235,
      "status": "ok",
      "error": null,
      "agent_ok": true,
      "iterations": 1
    },
    {
      "latency_seconds": 0.8711917819891823,
      "status": "ok",
      "error": null,
      "agent_ok": true,
      "iterations": 1
    },
    {
      "latency_seconds": 4.3093109100009315,
      "status": "ok",
      "error": null,
      "agent_ok": false,
      "iterations": 1
    },
    {
      "latency_seconds": 1.0077750089985784,
      "status": "ok",
      "error": null,
      "agent_ok": true,
      "iterations": 1
    },
    {
      "latency_seconds": 2.148039117004373,
      "status": "ok",
      "error": null,
      "agent_ok": true,
      "iterations": 1
    },
    {
      "latency_seconds": 1.2141529979999177,
      "status": "ok",
      "error": null,
      "agent_ok": true,
      "iterations": 1
    },
    {
      "latency_seconds": 0.9872844780038577,
      "status": "ok",
      "error": null,
      "agent_ok": true,
      "iterations": 1
    },
    {
      "latency_seconds": 3.4157784139970317,
      "status": "ok",
      "error": null,
      "agent_ok": true,
      "iterations": 1
    },
    {
      "latency_seconds": 1.6743727619905258,
      "status": "ok",
      "error": null,
      "agent_ok": true,
      "iterations": 1
    },
    {
      "latency_seconds": 0.9444282619951991,
      "status": "ok",
      "error": null,
      "agent_ok": true,
      "iterations": 1
    },
    {
      "latency_seconds": 0.8907475609885296,
      "status": "ok",
      "error": null,
      "agent_ok": true,
      "iterations": 1
    },
    {
      "latency_seconds": 1.418358527997043,
      "status": "ok",
      "error": null,
      "agent_ok": true,
      "iterations": 1
    },
    {
      "latency_seconds": 1.2864726900006644,
      "status": "ok",
      "error": null,
      "agent_ok": true,
      "iterations": 1
    },
    {
      "latency_seconds": 0.5962348470056895,
      "status": "ok",
      "error": null,
      "agent_ok": true,
      "iterations": 1
    },
    {
      "latency_seconds": 1.3769331310031703,
      "status": "ok",
      "error": null,
      "agent_ok": true,
      "iterations": 1
    },
    {
      "latency_seconds": 4.884280926999054,
      "status": "ok",
      "error": null,
      "agent_ok": true,
      "iterations": 1
    },
    {
      "latency_seconds": 1.0066608950000955,
      "status": "ok",
      "error": null,
      "agent_ok": true,
      "iterations": 1
    },
    {
      "latency_seconds": 1.3155098010029178,
      "status": "ok",
      "error": null,
      "agent_ok": true,
      "iterations": 1
    },
    {
      "latency_seconds": 0.8215129099990008,
      "status": "ok",
      "error": null,
      "agent_ok": true,
      "iterations": 1
    },
    {
      "latency_seconds": 3.8726784119935473,
      "status": "ok",
      "error": null,
      "agent_ok": true,
      "iterations": 1
    },
    {
      "latency_seconds": 1.0015303019899875,
      "status": "ok",
      "error": null,
      "agent_ok": true,
      "iterations": 1
    },
    {
      "latency_seconds": 2.2794370720075676,
      "status": "ok",
      "error": null,
      "agent_ok": true,
      "iterations": 1
    },
    {
      "latency_seconds": 0.7540552879945608,
      "status": "ok",
      "error": null,
      "agent_ok": true,
      "iterations": 1
    },
    {
      "latency_seconds": 0.9619465919968206,
      "status": "ok",
      "error": null,
      "agent_ok": true,
      "iterations": 1
    },
    {
      "latency_seconds": 2.316164346993901,
      "status": "ok",
      "error": null,
      "agent_ok": true,
      "iterations": 1
    },
    {
      "latency_seconds": 0.7414060099981725,
      "status": "ok",
      "error": null,
      "agent_ok": true,
      "iterations": 1
    },
    {
      "latency_seconds": 1.550667686999077,
      "status": "ok",
      "error": null,
      "agent_ok": true,
      "iterations": 1
    },
    {
      "latency_seconds": 0.7701410590088926,
      "status": "ok",
      "error": null,
      "agent_ok": true,
      "iterations": 1
    },
    {
      "latency_seconds": 0.6448577879928052,
      "status": "ok",
      "error": null,
      "agent_ok": true,
      "iterations": 1
    },
    {
      "latency_seconds": 0.5786049970047316,
      "status": "ok",
      "error": null,
      "agent_ok": true,
      "iterations": 1
    },
    {
      "latency_seconds": 3.660562180011766,
      "status": "ok",
      "error": null,
      "agent_ok": true,
      "iterations": 1
    },
    {
      "latency_seconds": 2.1424022749997675,
      "status": "ok",
      "error": null,
      "agent_ok": true,
      "iterations": 1
    },
    {
      "latency_seconds": 1.0462324350082781,
      "status": "ok",
      "error": null,
      "agent_ok": true,
      "iterations": 1
    },
    {
      "latency_seconds": 5.539954409992788,
      "status": "ok",
      "error": null,
      "agent_ok": true,
      "iterations": 1
    },
    {
      "latency_seconds": 1.4943003509979462,
      "status": "ok",
      "error": null,
      "agent_ok": true,
      "iterations": 1
    },
    {
      "latency_seconds": 0.83290183499048,
      "status": "ok",
      "error": null,
      "agent_ok": true,
      "iterations": 1
    },
    {
      "latency_seconds": 1.4495561980002094,
      "status": "ok",
      "error": null,
      "agent_ok": true,
      "iterations": 1
    },
    {
      "latency_seconds": 0.6962914720061235,
      "status": "ok",
      "error": null,
      "agent_ok": true,
      "iterations": 1
    },
    {
      "latency_seconds": 0.8018407939962344,
      "status": "ok",
      "error": null,
      "agent_ok": false,
      "iterations": 1
    },
    {
      "latency_seconds": 0.3813074259960558,
      "status": "ok",
      "error": null,
      "agent_ok": true,
      "iterations": 1
    },
    {
      "latency_seconds": 0.9914968230004888,
      "status": "ok",
      "error": null,
      "agent_ok": true,
      "iterations": 1
    },
    {
      "latency_seconds": 0.45082635899598245,
      "status": "ok",
      "error": null,
      "agent_ok": true,
      "iterations": 1
    },
    {
      "latency_seconds": 1.164174681995064,
      "status": "ok",
      "error": null,
      "agent_ok": true,
      "iterations": 1
    },
    {
      "latency_seconds": 1.8723098070040578,
      "status": "ok",
      "error": null,
      "agent_ok": true,
      "iterations": 1
    },
    {
      "latency_seconds": 3.464097538002534,
      "status": "ok",
      "error": null,
      "agent_ok": true,
      "iterations": 1
    },
    {
      "latency_seconds": 1.1125806229974842,
      "status": "ok",
      "error": null,
      "agent_ok": true,
      "iterations": 1
    },
    {
      "latency_seconds": 1.219010517001152,
      "status": "ok",
      "error": null,
      "agent_ok": true,
      "iterations": 1
    },
    {
      "latency_seconds": 0.6483395069953986,
      "status": "ok",
      "error": null,
      "agent_ok": true,
      "iterations": 1
    },
    {
      "latency_seconds": 0.5873124880017713,
      "status": "ok",
      "error": null,
      "agent_ok": true,
      "iterations": 1
    },
    {
      "latency_seconds": 0.5056298400013475,
      "status": "ok",
      "error": null,
      "agent_ok": true,
      "iterations": 1
    },
    {
      "latency_seconds": 1.00344168599986,
      "status": "ok",
      "error": null,
      "agent_ok": true,
      "iterations": 1
    },
    {
      "latency_seconds": 3.9722391609975602,
      "status": "ok",
      "error": null,
      "agent_ok": true,
      "iterations": 1
    },
    {
      "latency_seconds": 0.4479943810001714,
      "status": "ok",
      "error": null,
      "agent_ok": true,
      "iterations": 1
    },
    {
      "latency_seconds": 0.8518618389935,
      "status": "ok",
      "error": null,
      "agent_ok": true,
      "iterations": 1
    },
    {
      "latency_seconds": 0.4990898309915792,
      "status": "ok",
      "error": null,
      "agent_ok": true,
      "iterations": 1
    },
    {
      "latency_seconds": 0.6193786029907642,
      "status": "ok",
      "error": null,
      "agent_ok": true,
      "iterations": 1
    },
    {
      "latency_seconds": 1.3374893150030402,
      "status": "ok",
      "error": null,
      "agent_ok": true,
      "iterations": 1
    },
    {
      "latency_seconds": 0.7755423750058981,
      "status": "ok",
      "error": null,
      "agent_ok": true,
      "iterations": 1
    },
    {
      "latency_seconds": 0.6333734649961116,
      "status": "ok",
      "error": null,
      "agent_ok": true,
      "iterations": 1
    },
    {
      "latency_seconds": 0.7370182200102136,
      "status": "ok",
      "error": null,
      "agent_ok": true,
      "iterations": 1
    },
    {
      "latency_seconds": 1.2873729999992065,
      "status": "ok",
      "error": null,
      "agent_ok": true,
      "iterations": 1
    },
    {
      "latency_seconds": 0.8290230769925984,
      "status": "ok",
      "error": null,
      "agent_ok": true,
      "iterations": 1
    },
    {
      "latency_seconds": 0.4820760550064733,
      "status": "ok",
      "error": null,
      "agent_ok": true,
      "iterations": 1
    },
    {
      "latency_seconds": 1.8390878780046478,
      "status": "ok",
      "error": null,
      "agent_ok": true,
      "iterations": 1
    },
    {
      "latency_seconds": 0.31629343499662355,
      "status": "ok",
      "error": null,
      "agent_ok": true,
      "iterations": 1
    },
    {
      "latency_seconds": 1.851767407002626,
      "status": "ok",
      "error": null,
      "agent_ok": true,
      "iterations": 1
    },
    {
      "latency_seconds": 1.2967063269898063,
      "status": "ok",
      "error": null,
      "agent_ok": true,
      "iterations": 1
    },
    {
      "latency_seconds": 1.2526796309975907,
      "status": "ok",
      "error": null,
      "agent_ok": true,
      "iterations": 1
    },
    {
      "latency_seconds": 1.6974309350043768,
      "status": "ok",
      "error": null,
      "agent_ok": true,
      "iterations": 1
    },
    {
      "latency_seconds": 0.7969465050118743,
      "status": "ok",
      "error": null,
      "agent_ok": true,
      "iterations": 1
    },
    {
      "latency_seconds": 3.3523238799971296,
      "status": "ok",
      "error": null,
      "agent_ok": true,
      "iterations": 1
    },
    {
      "latency_seconds": 1.2777512439934071,
      "status": "ok",
      "error": null,
      "agent_ok": true,
      "iterations": 1
    },
    {
      "latency_seconds": 1.1397503659973154,
      "status": "ok",
      "error": null,
      "agent_ok": true,
      "iterations": 1
    },
    {
      "latency_seconds": 0.7061574560066219,
      "status": "ok",
      "error": null,
      "agent_ok": true,
      "iterations": 1
    },
    {
      "latency_seconds": 2.051225246003014,
      "status": "ok",
      "error": null,
      "agent_ok": true,
      "iterations": 1
    },
    {
      "latency_seconds": 1.0164617580012418,
      "status": "ok",
      "error": null,
      "agent_ok": true,
      "iterations": 1
    },
    {
      "latency_seconds": 1.155074260008405,
      "status": "ok",
      "error": null,
      "agent_ok": true,
      "iterations": 1
    },
    {
      "latency_seconds": 1.9106770109938225,
      "status": "ok",
      "error": null,
      "agent_ok": true,
      "iterations": 1
    },
    {
      "latency_seconds": 0.791243483996368,
      "status": "ok",
      "error": null,
      "agent_ok": true,
      "iterations": 1
    },
    {
      "latency_seconds": 0.8539460330066504,
      "status": "ok",
      "error": null,
      "agent_ok": true,
      "iterations": 1
    },
    {
      "latency_seconds": 0.48703881799883675,
      "status": "ok",
      "error": null,
      "agent_ok": true,
      "iterations": 1
    },
    {
      "latency_seconds": 0.8909571190015413,
      "status": "ok",
      "error": null,
      "agent_ok": true,
      "iterations": 1
    },
    {
      "latency_seconds": 1.358811619997141,
      "status": "ok",
      "error": null,
      "agent_ok": true,
      "iterations": 1
    },
    {
      "latency_seconds": 1.3518044349912088,
      "status": "ok",
      "error": null,
      "agent_ok": true,
      "iterations": 1
    },
    {
      "latency_seconds": 1.0463059329922544,
      "status": "ok",
      "error": null,
      "agent_ok": true,
      "iterations": 1
    },
    {
      "latency_seconds": 6.932624932989711,
      "status": "ok",
      "error": null,
      "agent_ok": true,
      "iterations": 1
    },
    {
      "latency_seconds": 1.3244574580021435,
      "status": "ok",
      "error": null,
      "agent_ok": true,
      "iterations": 1
    },
    {
      "latency_seconds": 0.6656009560101666,
      "status": "ok",
      "error": null,
      "agent_ok": true,
      "iterations": 1
    },
    {
      "latency_seconds": 1.5483106400060933,
      "status": "ok",
      "error": null,
      "agent_ok": true,
      "iterations": 1
    },
    {
      "latency_seconds": 0.5108907310059294,
      "status": "ok",
      "error": null,
      "agent_ok": true,
      "iterations": 1
    },
    {
      "latency_seconds": 1.1040800979972119,
      "status": "ok",
      "error": null,
      "agent_ok": true,
      "iterations": 1
    },
    {
      "latency_seconds": 2.4128221290011425,
      "status": "ok",
      "error": null,
      "agent_ok": true,
      "iterations": 1
    },
    {
      "latency_seconds": 0.7487982170132454,
      "status": "ok",
      "error": null,
      "agent_ok": true,
      "iterations": 1
    },
    {
      "latency_seconds": 3.4433324779965915,
      "status": "ok",
      "error": null,
      "agent_ok": true,
      "iterations": 1
    },
    {
      "latency_seconds": 0.7847800739982631,
      "status": "ok",
      "error": null,
      "agent_ok": true,
      "iterations": 1
    },
    {
      "latency_seconds": 0.516180903010536,
      "status": "ok",
      "error": null,
      "agent_ok": true,
      "iterations": 1
    },
    {
      "latency_seconds": 1.796868129997165,
      "status": "ok",
      "error": null,
      "agent_ok": true,
      "iterations": 1
    },
    {
      "latency_seconds": 1.5305250609962968,
      "status": "ok",
      "error": null,
      "agent_ok": true,
      "iterations": 1
    },
    {
      "latency_seconds": 0.46182978300203104,
      "status": "ok",
      "error": null,
      "agent_ok": true,
      "iterations": 1
    },
    {
      "latency_seconds": 2.170752445003018,
      "status": "ok",
      "error": null,
      "agent_ok": true,
      "iterations": 1
    },
    {
      "latency_seconds": 0.7960826700000325,
      "status": "ok",
      "error": null,
      "agent_ok": true,
      "iterations": 1
    },
    {
      "latency_seconds": 1.6340136350045213,
      "status": "ok",
      "error": null,
      "agent_ok": true,
      "iterations": 1
    },
    {
      "latency_seconds": 1.6528999669972109,
      "status": "ok",
      "error": null,
      "agent_ok": true,
      "iterations": 1
    },
    {
      "latency_seconds": 0.7914549090055516,
      "status": "ok",
      "error": null,
      "agent_ok": true,
      "iterations": 1
    },
    {
      "latency_seconds": 4.32017790300597,
      "status": "ok",
      "error": null,
      "agent_ok": true,
      "iterations": 1
    },
    {
      "latency_seconds": 1.4084405079920543,
      "status": "ok",
      "error": null,
      "agent_ok": true,
      "iterations": 1
    },
    {
      "latency_seconds": 0.8246983550052391,
      "status": "ok",
      "error": null,
      "agent_ok": true,
      "iterations": 1
    },
    {
      "latency_seconds": 1.3370250120060518,
      "status": "ok",
      "error": null,
      "agent_ok": true,
      "iterations": 1
    },
    {
      "latency_seconds": 1.0111518560006516,
      "status": "ok",
      "error": null,
      "agent_ok": true,
      "iterations": 1
    },
    {
      "latency_seconds": 0.9796064230031334,
      "status": "ok",
      "error": null,
      "agent_ok": true,
      "iterations": 1
    },
    {
      "latency_seconds": 0.9175807260035072,
      "status": "ok",
      "error": null,
      "agent_ok": true,
      "iterations": 1
    },
    {
      "latency_seconds": 0.8824281909910496,
      "status": "ok",
      "error": null,
      "agent_ok": true,
      "iterations": 1
    },
    {
      "latency_seconds": 0.8227286320034182,
      "status": "ok",
      "error": null,
      "agent_ok": true,
      "iterations": 1
    },
    {
      "latency_seconds": 0.8225604990002466,
      "status": "ok",
      "error": null,
      "agent_ok": true,
      "iterations": 1
    },
    {
      "latency_seconds": 0.5722060710104415,
      "status": "ok",
      "error": null,
      "agent_ok": true,
      "iterations": 1
    },
    {
      "latency_seconds": 0.8558313100074884,
      "status": "ok",
      "error": null,
      "agent_ok": true,
      "iterations": 1
    },
    {
      "latency_seconds": 1.6248369569948409,
      "status": "ok",
      "error": null,
      "agent_ok": true,
      "iterations": 1
    },
    {
      "latency_seconds": 0.9864463340054499,
      "status": "ok",
      "error": null,
      "agent_ok": true,
      "iterations": 1
    },
    {
      "latency_seconds": 1.0683950149978045,
      "status": "ok",
      "error": null,
      "agent_ok": true,
      "iterations": 1
    },
    {
      "latency_seconds": 1.0385182830068516,
      "status": "ok",
      "error": null,
      "agent_ok": true,
      "iterations": 1
    },
    {
      "latency_seconds": 1.8016557740047574,
      "status": "ok",
      "error": null,
      "agent_ok": true,
      "iterations": 1
    },
    {
      "latency_seconds": 4.62446823900973,
      "status": "ok",
      "error": null,
      "agent_ok": true,
      "iterations": 1
    },
    {
      "latency_seconds": 0.9852324529929319,
      "status": "ok",
      "error": null,
      "agent_ok": true,
      "iterations": 1
    },
    {
      "latency_seconds": 1.3829291629954241,
      "status": "ok",
      "error": null,
      "agent_ok": true,
      "iterations": 1
    },
    {
      "latency_seconds": 0.7673318949964596,
      "status": "ok",
      "error": null,
      "agent_ok": true,
      "iterations": 1
    },
    {
      "latency_seconds": 1.1810778570070397,
      "status": "ok",
      "error": null,
      "agent_ok": true,
      "iterations": 1
    },
    {
      "latency_seconds": 0.9188262279931223,
      "status": "ok",
      "error": null,
      "agent_ok": true,
      "iterations": 1
    },
    {
      "latency_seconds": 1.3374787109933095,
      "status": "ok",
      "error": null,
      "agent_ok": true,
      "iterations": 1
    },
    {
      "latency_seconds": 0.6735789560043486,
      "status": "ok",
      "error": null,
      "agent_ok": true,
      "iterations": 1
    },
    {
      "latency_seconds": 6.494819846004248,
      "status": "ok",
      "error": null,
      "agent_ok": true,
      "iterations": 1
    },
    {
      "latency_seconds": 3.8400071329961065,
      "status": "ok",
      "error": null,
      "agent_ok": true,
      "iterations": 1
    },
    {
      "latency_seconds": 0.4420170369994594,
      "status": "ok",
      "error": null,
      "agent_ok": true,
      "iterations": 1
    },
    {
      "latency_seconds": 0.27566744599607773,
      "status": "ok",
      "error": null,
      "agent_ok": true,
      "iterations": 1
    },
    {
      "latency_seconds": 2.347508145001484,
      "status": "ok",
      "error": null,
      "agent_ok": true,
      "iterations": 1
    },
    {
      "latency_seconds": 5.121003252992523,
      "status": "ok",
      "error": null,
      "agent_ok": true,
      "iterations": 1
    },
    {
      "latency_seconds": 1.4321146349975606,
      "status": "ok",
      "error": null,
      "agent_ok": true,
      "iterations": 1
    },
    {
      "latency_seconds": 0.6167795149958692,
      "status": "ok",
      "error": null,
      "agent_ok": true,
      "iterations": 1
    },
    {
      "latency_seconds": 2.0747981239983346,
      "status": "ok",
      "error": null,
      "agent_ok": true,
      "iterations": 1
    },
    {
      "latency_seconds": 0.6900598259962862,
      "status": "ok",
      "error": null,
      "agent_ok": true,
      "iterations": 1
    },
    {
      "latency_seconds": 1.1387699089973466,
      "status": "ok",
      "error": null,
      "agent_ok": true,
      "iterations": 1
    },
    {
      "latency_seconds": 2.341560661996482,
      "status": "ok",
      "error": null,
      "agent_ok": true,
      "iterations": 1
    },
    {
      "latency_seconds": 4.926311970004463,
      "status": "ok",
      "error": null,
      "agent_ok": false,
      "iterations": 1
    },
    {
      "latency_seconds": 0.835784145994694,
      "status": "ok",
      "error": null,
      "agent_ok": true,
      "iterations": 1
    },
    {
      "latency_seconds": 0.9758187709958293,
      "status": "ok",
      "error": null,
      "agent_ok": true,
      "iterations": 1
    },
    {
      "latency_seconds": 1.5890701699972851,
      "status": "ok",
      "error": null,
      "agent_ok": true,
      "iterations": 1
    },
    {
      "latency_seconds": 4.308523278989014,
      "status": "ok",
      "error": null,
      "agent_ok": true,
      "iterations": 1
    },
    {
      "latency_seconds": 1.1873900150094414,
      "status": "ok",
      "error": null,
      "agent_ok": true,
      "iterations": 1
    },
    {
      "latency_seconds": 2.898548283003038,
      "status": "ok",
      "error": null,
      "agent_ok": false,
      "iterations": 1
    },
    {
      "latency_seconds": 1.2384310449997429,
      "status": "ok",
      "error": null,
      "agent_ok": true,
      "iterations": 1
    },
    {
      "latency_seconds": 1.153650211999775,
      "status": "ok",
      "error": null,
      "agent_ok": true,
      "iterations": 1
    },
    {
      "latency_seconds": 1.5197148419974837,
      "status": "ok",
      "error": null,
      "agent_ok": true,
      "iterations": 1
    },
    {
      "latency_seconds": 5.932133228008752,
      "status": "ok",
      "error": null,
      "agent_ok": true,
      "iterations": 1
    },
    {
      "latency_seconds": 1.1298059560067486,
      "status": "ok",
      "error": null,
      "agent_ok": true,
      "iterations": 1
    },
    {
      "latency_seconds": 0.9806980520079378,
      "status": "ok",
      "error": null,
      "agent_ok": true,
      "iterations": 1
    },
    {
      "latency_seconds": 1.2810437669977546,
      "status": "ok",
      "error": null,
      "agent_ok": true,
      "iterations": 1
    },
    {
      "latency_seconds": 0.3020616029971279,
      "status": "ok",
      "error": null,
      "agent_ok": true,
      "iterations": 1
    },
    {
      "latency_seconds": 1.1792905179900117,
      "status": "ok",
      "error": null,
      "agent_ok": true,
      "iterations": 1
    },
    {
      "latency_seconds": 1.016556913004024,
      "status": "ok",
      "error": null,
      "agent_ok": true,
      "iterations": 1
    },
    {
      "latency_seconds": 0.6581251799943857,
      "status": "ok",
      "error": null,
      "agent_ok": true,
      "iterations": 1
    },
    {
      "latency_seconds": 0.9645356340042781,
      "status": "ok",
      "error": null,
      "agent_ok": true,
      "iterations": 1
    },
    {
      "latency_seconds": 3.283712481992552,
      "status": "ok",
      "error": null,
      "agent_ok": true,
      "iterations": 1
    },
    {
      "latency_seconds": 0.8116594029997941,
      "status": "ok",
      "error": null,
      "agent_ok": true,
      "iterations": 1
    },
    {
      "latency_seconds": 0.729089856002247,
      "status": "ok",
      "error": null,
      "agent_ok": true,
      "iterations": 1
    },
    {
      "latency_seconds": 3.5367657149909064,
      "status": "ok",
      "error": null,
      "agent_ok": true,
      "iterations": 1
    },
    {
      "latency_seconds": 0.7750705360085703,
      "status": "ok",
      "error": null,
      "agent_ok": true,
      "iterations": 1
    },
    {
      "latency_seconds": 1.4744724379997933,
      "status": "ok",
      "error": null,
      "agent_ok": true,
      "iterations": 1
    },
    {
      "latency_seconds": 0.9504735219961731,
      "status": "ok",
      "error": null,
      "agent_ok": true,
      "iterations": 1
    },
    {
      "latency_seconds": 0.6843076509976527,
      "status": "ok",
      "error": null,
      "agent_ok": true,
      "iterations": 1
    },
    {
      "latency_seconds": 0.4680320609913906,
      "status": "ok",
      "error": null,
      "agent_ok": true,
      "iterations": 1
    },
    {
      "latency_seconds": 1.0304034430009779,
      "status": "ok",
      "error": null,
      "agent_ok": true,
      "iterations": 1
    },
    {
      "latency_seconds": 0.8485509999882197,
      "status": "ok",
      "error": null,
      "agent_ok": true,
      "iterations": 1
    },
    {
      "latency_seconds": 1.0515515629958827,
      "status": "ok",
      "error": null,
      "agent_ok": true,
      "iterations": 1
    },
    {
      "latency_seconds": 0.9658912729937583,
      "status": "ok",
      "error": null,
      "agent_ok": true,
      "iterations": 1
    },
    {
      "latency_seconds": 3.5292153890040936,
      "status": "ok",
      "error": null,
      "agent_ok": true,
      "iterations": 1
    },
    {
      "latency_seconds": 0.33753917600552086,
      "status": "ok",
      "error": null,
      "agent_ok": true,
      "iterations": 1
    },
    {
      "latency_seconds": 0.7488973769941367,
      "status": "ok",
      "error": null,
      "agent_ok": true,
      "iterations": 1
    },
    {
      "latency_seconds": 0.9775356039899634,
      "status": "ok",
      "error": null,
      "agent_ok": true,
      "iterations": 1
    },
    {
      "latency_seconds": 1.9333507569972426,
      "status": "ok",
      "error": null,
      "agent_ok": true,
      "iterations": 1
    },
    {
      "latency_seconds": 1.273541128000943,
      "status": "ok",
      "error": null,
      "agent_ok": true,
      "iterations": 1
    },
    {
      "latency_seconds": 0.7852869690104853,
      "status": "ok",
      "error": null,
      "agent_ok": true,
      "iterations": 1
    },
    {
      "latency_seconds": 0.632322199002374,
      "status": "ok",
      "error": null,
      "agent_ok": true,
      "iterations": 1
    },
    {
      "latency_seconds": 3.7076391039881855,
      "status": "ok",
      "error": null,
      "agent_ok": true,
      "iterations": 1
    },
    {
      "latency_seconds": 3.227464007009985,
      "status": "ok",
      "error": null,
      "agent_ok": true,
      "iterations": 1
    },
    {
      "latency_seconds": 1.6503036100039026,
      "status": "ok",
      "error": null,
      "agent_ok": true,
      "iterations": 1
    },
    {
      "latency_seconds": 0.6276269520021742,
      "status": "ok",
      "error": null,
      "agent_ok": true,
      "iterations": 1
    },
    {
      "latency_seconds": 0.675000485003693,
      "status": "ok",
      "error": null,
      "agent_ok": true,
      "iterations": 1
    },
    {
      "latency_seconds": 3.5799150509992614,
      "status": "ok",
      "error": null,
      "agent_ok": true,
      "iterations": 1
    },
    {
      "latency_seconds": 1.3447936909942655,
      "status": "ok",
      "error": null,
      "agent_ok": true,
      "iterations": 1
    },
    {
      "latency_seconds": 1.725929417007137,
      "status": "ok",
      "error": null,
      "agent_ok": true,
      "iterations": 1
    },
    {
      "latency_seconds": 0.671315849001985,
      "status": "ok",
      "error": null,
      "agent_ok": true,
      "iterations": 1
    },
    {
      "latency_seconds": 1.1879580090026138,
      "status": "ok",
      "error": null,
      "agent_ok": false,
      "iterations": 1
    },
    {
      "latency_seconds": 1.1441140609967988,
      "status": "ok",
      "error": null,
      "agent_ok": true,
      "iterations": 1
    },
    {
      "latency_seconds": 0.6748624750034651,
      "status": "ok",
      "error": null,
      "agent_ok": true,
      "iterations": 1
    },
    {
      "latency_seconds": 0.25131477700779215,
      "status": "ok",
      "error": null,
      "agent_ok": true,
      "iterations": 1
    },
    {
      "latency_seconds": 0.4780359779979335,
      "status": "ok",
      "error": null,
      "agent_ok": true,
      "iterations": 1
    },
    {
      "latency_seconds": 1.244761063993792,
      "status": "ok",
      "error": null,
      "agent_ok": true,
      "iterations": 1
    },
    {
      "latency_seconds": 0.5527653919998556,
      "status": "ok",
      "error": null,
      "agent_ok": true,
      "iterations": 1
    },
    {
      "latency_seconds": 1.2304728099989006,
      "status": "ok",
      "error": null,
      "agent_ok": true,
      "iterations": 1
    },
    {
      "latency_seconds": 0.39737635100027546,
      "status": "ok",
      "error": null,
      "agent_ok": true,
      "iterations": 1
    },
    {
      "latency_seconds": 1.142624097992666,
      "status": "ok",
      "error": null,
      "agent_ok": true,
      "iterations": 1
    },
    {
      "latency_seconds": 0.5558741389977513,
      "status": "ok",
      "error": null,
      "agent_ok": true,
      "iterations": 1
    },
    {
      "latency_seconds": 0.8205965240049409,
      "status": "ok",
      "error": null,
      "agent_ok": true,
      "iterations": 1
    },
    {
      "latency_seconds": 0.9158044089999748,
      "status": "ok",
      "error": null,
      "agent_ok": true,
      "iterations": 1
    },
    {
      "latency_seconds": 0.6228233659930993,
      "status": "ok",
      "error": null,
      "agent_ok": true,
      "iterations": 1
    },
    {
      "latency_seconds": 0.75022556699696,
      "status": "ok",
      "error": null,
      "agent_ok": true,
      "iterations": 1
    },
    {
      "latency_seconds": 3.5229738570051268,
      "status": "ok",
      "error": null,
      "agent_ok": false,
      "iterations": 1
    },
    {
      "latency_seconds": 1.142516590989544,
      "status": "ok",
      "error": null,
      "agent_ok": false,
      "iterations": 1
    },
    {
      "latency_seconds": 0.5690699989936547,
      "status": "ok",
      "error": null,
      "agent_ok": true,
      "iterations": 1
    },
    {
      "latency_seconds": 0.6344537330005551,
      "status": "ok",
      "error": null,
      "agent_ok": true,
      "iterations": 1
    },
    {
      "latency_seconds": 1.356956067000283,
      "status": "ok",
      "error": null,
      "agent_ok": true,
      "iterations": 1
    },
    {
      "latency_seconds": 0.7189164860028541,
      "status": "ok",
      "error": null,
      "agent_ok": true,
      "iterations": 1
    },
    {
      "latency_seconds": 4.411715024994919,
      "status": "ok",
      "error": null,
      "agent_ok": true,
      "iterations": 1
    },
    {
      "latency_seconds": 0.8281510979868472,
      "status": "ok",
      "error": null,
      "agent_ok": true,
      "iterations": 1
    },
    {
      "latency_seconds": 0.7641270799940685,
      "status": "ok",
      "error": null,
      "agent_ok": true,
      "iterations": 1
    },
    {
      "latency_seconds": 3.7761359729920514,
      "status": "ok",
      "error": null,
      "agent_ok": true,
      "iterations": 1
    },
    {
      "latency_seconds": 1.5251985450013308,
      "status": "ok",
      "error": null,
      "agent_ok": true,
      "iterations": 1
    },
    {
      "latency_seconds": 3.474069720992702,
      "status": "ok",
      "error": null,
      "agent_ok": true,
      "iterations": 1
    },
    {
      "latency_seconds": 1.0382971020007972,
      "status": "ok",
      "error": null,
      "agent_ok": true,
      "iterations": 1
    },
    {
      "latency_seconds": 1.0041627640021034,
      "status": "ok",
      "error": null,
      "agent_ok": true,
      "iterations": 1
    },
    {
      "latency_seconds": 2.4233456029905938,
      "status": "ok",
      "error": null,
      "agent_ok": true,
      "iterations": 1
    },
    {
      "latency_seconds": 1.4049019869999029,
      "status": "ok",
      "error": null,
      "agent_ok": true,
      "iterations": 1
    },
    {
      "latency_seconds": 1.028916601993842,
      "status": "ok",
      "error": null,
      "agent_ok": true,
      "iterations": 1
    },
    {
      "latency_seconds": 1.6439875840005698,
      "status": "ok",
      "error": null,
      "agent_ok": true,
      "iterations": 1
    },
    {
      "latency_seconds": 1.3869155230058823,
      "status": "ok",
      "error": null,
      "agent_ok": true,
      "iterations": 1
    },
    {
      "latency_seconds": 0.9501565690006828,
      "status": "ok",
      "error": null,
      "agent_ok": true,
      "iterations": 1
    },
    {
      "latency_seconds": 1.0950313749926863,
      "status": "ok",
      "error": null,
      "agent_ok": true,
      "iterations": 1
    },
    {
      "latency_seconds": 0.6799125919933431,
      "status": "ok",
      "error": null,
      "agent_ok": true,
      "iterations": 1
    },
    {
      "latency_seconds": 0.4670151979953516,
      "status": "ok",
      "error": null,
      "agent_ok": true,
      "iterations": 1
    },
    {
      "latency_seconds": 0.683812030008994,
      "status": "ok",
      "error": null,
      "agent_ok": true,
      "iterations": 1
    },
    {
      "latency_seconds": 1.0361761759995716,
      "status": "ok",
      "error": null,
      "agent_ok": true,
      "iterations": 1
    },
    {
      "latency_seconds": 4.067460556994774,
      "status": "ok",
      "error": null,
      "agent_ok": true,
      "iterations": 1
    },
    {
      "latency_seconds": 1.228608791003353,
      "status": "ok",
      "error": null,
      "agent_ok": true,
      "iterations": 1
    },
    {
      "latency_seconds": 0.46704977499030065,
      "status": "ok",
      "error": null,
      "agent_ok": true,
      "iterations": 1
    },
    {
      "latency_seconds": 1.0658076819963753,
      "status": "ok",
      "error": null,
      "agent_ok": true,
      "iterations": 1
    },
    {
      "latency_seconds": 2.3490350729989586,
      "status": "ok",
      "error": null,
      "agent_ok": true,
      "iterations": 1
    },
    {
      "latency_seconds": 0.4731081659992924,
      "status": "ok",
      "error": null,
      "agent_ok": true,
      "iterations": 1
    },
    {
      "latency_seconds": 0.965394439001102,
      "status": "ok",
      "error": null,
      "agent_ok": true,
      "iterations": 1
    },
    {
      "latency_seconds": 1.7183007709973026,
      "status": "ok",
      "error": null,
      "agent_ok": true,
      "iterations": 1
    },
    {
      "latency_seconds": 5.434212544001639,
      "status": "ok",
      "error": null,
      "agent_ok": true,
      "iterations": 1
    },
    {
      "latency_seconds": 0.5045488820032915,
      "status": "ok",
      "error": null,
      "agent_ok": true,
      "iterations": 1
    },
    {
      "latency_seconds": 1.047690633989987,
      "status": "ok",
      "error": null,
      "agent_ok": true,
      "iterations": 1
    },
    {
      "latency_seconds": 1.3476661940076156,
      "status": "ok",
      "error": null,
      "agent_ok": true,
      "iterations": 1
    },
    {
      "latency_seconds": 1.1080289450037526,
      "status": "ok",
      "error": null,
      "agent_ok": true,
      "iterations": 1
    },
    {
      "latency_seconds": 0.46438664200832136,
      "status": "ok",
      "error": null,
      "agent_ok": true,
      "iterations": 1
    },
    {
      "latency_seconds": 0.7135112670075614,
      "status": "ok",
      "error": null,
      "agent_ok": true,
      "iterations": 1
    },
    {
      "latency_seconds": 0.6753987829870312,
      "status": "ok",
      "error": null,
      "agent_ok": true,
      "iterations": 1
    },
    {
      "latency_seconds": 1.191428095989977,
      "status": "ok",
      "error": null,
      "agent_ok": true,
      "iterations": 1
    },
    {
      "latency_seconds": 2.7415709820052143,
      "status": "ok",
      "error": null,
      "agent_ok": true,
      "iterations": 1
    },
    {
      "latency_seconds": 0.7650616570026614,
      "status": "ok",
      "error": null,
      "agent_ok": true,
      "iterations": 1
    },
    {
      "latency_seconds": 0.5886249370087171,
      "status": "ok",
      "error": null,
      "agent_ok": true,
      "iterations": 1
    },
    {
      "latency_seconds": 0.2843564009963302,
      "status": "ok",
      "error": null,
      "agent_ok": true,
      "iterations": 1
    },
    {
      "latency_seconds": 0.5555279149994021,
      "status": "ok",
      "error": null,
      "agent_ok": true,
      "iterations": 1
    },
    {
      "latency_seconds": 1.4895110730140004,
      "status": "ok",
      "error": null,
      "agent_ok": true,
      "iterations": 1
    },
    {
      "latency_seconds": 1.4229422409989638,
      "status": "ok",
      "error": null,
      "agent_ok": true,
      "iterations": 1
    },
    {
      "latency_seconds": 0.6980138710059691,
      "status": "ok",
      "error": null,
      "agent_ok": true,
      "iterations": 1
    },
    {
      "latency_seconds": 0.7039044669945724,
      "status": "ok",
      "error": null,
      "agent_ok": true,
      "iterations": 1
    },
    {
      "latency_seconds": 1.6761754720064346,
      "status": "ok",
      "error": null,
      "agent_ok": true,
      "iterations": 1
    },
    {
      "latency_seconds": 0.7408937380096177,
      "status": "ok",
      "error": null,
      "agent_ok": true,
      "iterations": 1
    },
    {
      "latency_seconds": 1.0679464480053866,
      "status": "ok",
      "error": null,
      "agent_ok": true,
      "iterations": 1
    },
    {
      "latency_seconds": 0.6939416380046168,
      "status": "ok",
      "error": null,
      "agent_ok": true,
      "iterations": 1
    },
    {
      "latency_seconds": 0.6613211299991235,
      "status": "ok",
      "error": null,
      "agent_ok": true,
      "iterations": 1
    },
    {
      "latency_seconds": 1.0520468149916269,
      "status": "ok",
      "error": null,
      "agent_ok": true,
      "iterations": 1
    },
    {
      "latency_seconds": 0.5909266960079549,
      "status": "ok",
      "error": null,
      "agent_ok": true,
      "iterations": 1
    },
    {
      "latency_seconds": 1.0738284999970347,
      "status": "ok",
      "error": null,
      "agent_ok": true,
      "iterations": 1
    },
    {
      "latency_seconds": 2.4228095300059067,
      "status": "ok",
      "error": null,
      "agent_ok": true,
      "iterations": 1
    },
    {
      "latency_seconds": 1.3031878000037977,
      "status": "ok",
      "error": null,
      "agent_ok": true,
      "iterations": 1
    },
    {
      "latency_seconds": 0.9232952329912223,
      "status": "ok",
      "error": null,
      "agent_ok": true,
      "iterations": 1
    },
    {
      "latency_seconds": 1.0314925819984637,
      "status": "ok",
      "error": null,
      "agent_ok": true,
      "iterations": 1
    },
    {
      "latency_seconds": 2.7815921360015636,
      "status": "ok",
      "error": null,
      "agent_ok": true,
      "iterations": 1
    },
    {
      "latency_seconds": 3.6641392250021454,
      "status": "ok",
      "error": null,
      "agent_ok": true,
      "iterations": 1
    },
    {
      "latency_seconds": 0.6652049429976614,
      "status": "ok",
      "error": null,
      "agent_ok": true,
      "iterations": 1
    },
    {
      "latency_seconds": 0.7732221820042469,
      "status": "ok",
      "error": null,
      "agent_ok": true,
      "iterations": 1
    },
    {
      "latency_seconds": 1.2929283910052618,
      "status": "ok",
      "error": null,
      "agent_ok": true,
      "iterations": 1
    },
    {
      "latency_seconds": 1.0745259129907936,
      "status": "ok",
      "error": null,
      "agent_ok": true,
      "iterations": 1
    },
    {
      "latency_seconds": 1.495983407003223,
      "status": "ok",
      "error": null,
      "agent_ok": true,
      "iterations": 1
    },
    {
      "latency_seconds": 0.9118386839982122,
      "status": "ok",
      "error": null,
      "agent_ok": true,
      "iterations": 1
    },
    {
      "latency_seconds": 0.34619133999512997,
      "status": "ok",
      "error": null,
      "agent_ok": true,
      "iterations": 1
    },
    {
      "latency_seconds": 0.78361250400485,
      "status": "ok",
      "error": null,
      "agent_ok": true,
      "iterations": 1
    },
    {
      "latency_seconds": 0.8964416660019197,
      "status": "ok",
      "error": null,
      "agent_ok": true,
      "iterations": 1
    },
    {
      "latency_seconds": 1.0904209900036221,
      "status": "ok",
      "error": null,
      "agent_ok": true,
      "iterations": 1
    },
    {
      "latency_seconds": 0.7830518730042968,
      "status": "ok",
      "error": null,
      "agent_ok": true,
      "iterations": 1
    },
    {
      "latency_seconds": 0.9067236100090668,
      "status": "ok",
      "error": null,
      "agent_ok": true,
      "iterations": 1
    },
    {
      "latency_seconds": 1.3307172209897544,
      "status": "ok",
      "error": null,
      "agent_ok": true,
      "iterations": 1
    },
    {
      "latency_seconds": 0.7604094209964387,
      "status": "ok",
      "error": null,
      "agent_ok": true,
      "iterations": 1
    },
    {
      "latency_seconds": 0.6913189500046428,
      "status": "ok",
      "error": null,
      "agent_ok": true,
      "iterations": 1
    },
    {
      "latency_seconds": 2.7278256860008696,
      "status": "ok",
      "error": null,
      "agent_ok": true,
      "iterations": 1
    },
    {
      "latency_seconds": 0.8341344049986219,
      "status": "ok",
      "error": null,
      "agent_ok": true,
      "iterations": 1
    },
    {
      "latency_seconds": 0.6462252960045589,
      "status": "ok",
      "error": null,
      "agent_ok": true,
      "iterations": 1
    },
    {
      "latency_seconds": 0.5562585870065959,
      "status": "ok",
      "error": null,
      "agent_ok": true,
      "iterations": 1
    },
    {
      "latency_seconds": 2.4488366919977125,
      "status": "ok",
      "error": null,
      "agent_ok": true,
      "iterations": 1
    },
    {
      "latency_seconds": 2.5756674820004264,
      "status": "ok",
      "error": null,
      "agent_ok": true,
      "iterations": 1
    },
    {
      "latency_seconds": 4.663957798999036,
      "status": "ok",
      "error": null,
      "agent_ok": true,
      "iterations": 1
    },
    {
      "latency_seconds": 0.5021684609964723,
      "status": "ok",
      "error": null,
      "agent_ok": true,
      "iterations": 1
    },
    {
      "latency_seconds": 1.1691417319962056,
      "status": "ok",
      "error": null,
      "agent_ok": true,
      "iterations": 1
    },
    {
      "latency_seconds": 0.5979041399987182,
      "status": "ok",
      "error": null,
      "agent_ok": true,
      "iterations": 1
    },
    {
      "latency_seconds": 3.6394851750083035,
      "status": "ok",
      "error": null,
      "agent_ok": true,
      "iterations": 1
    },
    {
      "latency_seconds": 1.0238728490076028,
      "status": "ok",
      "error": null,
      "agent_ok": true,
      "iterations": 1
    },
    {
      "latency_seconds": 0.46989765799662564,
      "status": "ok",
      "error": null,
      "agent_ok": true,
      "iterations": 1
    },
    {
      "latency_seconds": 0.6008140500052832,
      "status": "ok",
      "error": null,
      "agent_ok": true,
      "iterations": 1
    },
    {
      "latency_seconds": 1.2022112249978818,
      "status": "ok",
      "error": null,
      "agent_ok": true,
      "iterations": 1
    },
    {
      "latency_seconds": 4.956552140996791,
      "status": "ok",
      "error": null,
      "agent_ok": true,
      "iterations": 1
    },
    {
      "latency_seconds": 0.6980117259954568,
      "status": "ok",
      "error": null,
      "agent_ok": true,
      "iterations": 1
    },
    {
      "latency_seconds": 1.2200912240077741,
      "status": "ok",
      "error": null,
      "agent_ok": true,
      "iterations": 1
    },
    {
      "latency_seconds": 0.9237772190099349,
      "status": "ok",
      "error": null,
      "agent_ok": true,
      "iterations": 1
    },
    {
      "latency_seconds": 1.0883650189934997,
      "status": "ok",
      "error": null,
      "agent_ok": true,
      "iterations": 1
    },
    {
      "latency_seconds": 0.5056690479977988,
      "status": "ok",
      "error": null,
      "agent_ok": true,
      "iterations": 1
    },
    {
      "latency_seconds": 2.5715686100011226,
      "status": "ok",
      "error": null,
      "agent_ok": true,
      "iterations": 1
    },
    {
      "latency_seconds": 1.0264628550066845,
      "status": "ok",
      "error": null,
      "agent_ok": true,
      "iterations": 1
    },
    {
      "latency_seconds": 0.816269827002543,
      "status": "ok",
      "error": null,
      "agent_ok": true,
      "iterations": 1
    },
    {
      "latency_seconds": 0.7510566829878371,
      "status": "ok",
      "error": null,
      "agent_ok": true,
      "iterations": 1
    },
    {
      "latency_seconds": 2.862250207006582,
      "status": "ok",
      "error": null,
      "agent_ok": true,
      "iterations": 1
    },
    {
      "latency_seconds": 2.1240693860017927,
      "status": "ok",
      "error": null,
      "agent_ok": false,
      "iterations": 1
    },
    {
      "latency_seconds": 1.5958128689962905,
      "status": "ok",
      "error": null,
      "agent_ok": true,
      "iterations": 1
    },
    {
      "latency_seconds": 2.1136953530076426,
      "status": "ok",
      "error": null,
      "agent_ok": true,
      "iterations": 1
    },
    {
      "latency_seconds": 1.4480484550003894,
      "status": "ok",
      "error": null,
      "agent_ok": true,
      "iterations": 1
    },
    {
      "latency_seconds": 1.3554974990111077,
      "status": "ok",
      "error": null,
      "agent_ok": true,
      "iterations": 1
    },
    {
      "latency_seconds": 1.3802324830030557,
      "status": "ok",
      "error": null,
      "agent_ok": true,
      "iterations": 1
    },
    {
      "latency_seconds": 1.2089772459876258,
      "status": "ok",
      "error": null,
      "agent_ok": true,
      "iterations": 1
    },
    {
      "latency_seconds": 0.9246150230028434,
      "status": "ok",
      "error": null,
      "agent_ok": true,
      "iterations": 1
    },
    {
      "latency_seconds": 3.959195813993574,
      "status": "ok",
      "error": null,
      "agent_ok": true,
      "iterations": 1
    },
    {
      "latency_seconds": 0.5194398009916767,
      "status": "ok",
      "error": null,
      "agent_ok": true,
      "iterations": 1
    },
    {
      "latency_seconds": 0.6161725779966218,
      "status": "ok",
      "error": null,
      "agent_ok": true,
      "iterations": 1
    },
    {
      "latency_seconds": 1.6248627510067308,
      "status": "ok",
      "error": null,
      "agent_ok": true,
      "iterations": 1
    },
    {
      "latency_seconds": 1.055075153009966,
      "status": "ok",
      "error": null,
      "agent_ok": true,
      "iterations": 1
    },
    {
      "latency_seconds": 1.5893266479979502,
      "status": "ok",
      "error": null,
      "agent_ok": true,
      "iterations": 1
    },
    {
      "latency_seconds": 1.4500133480032673,
      "status": "ok",
      "error": null,
      "agent_ok": true,
      "iterations": 1
    },
    {
      "latency_seconds": 1.2440430510032456,
      "status": "ok",
      "error": null,
      "agent_ok": true,
      "iterations": 1
    },
    {
      "latency_seconds": 1.139783118997002,
      "status": "ok",
      "error": null,
      "agent_ok": true,
      "iterations": 1
    },
    {
      "latency_seconds": 0.8326334839948686,
      "status": "ok",
      "error": null,
      "agent_ok": true,
      "iterations": 1
    },
    {
      "latency_seconds": 0.7377447809994919,
      "status": "ok",
      "error": null,
      "agent_ok": true,
      "iterations": 1
    },
    {
      "latency_seconds": 3.158783894003136,
      "status": "ok",
      "error": null,
      "agent_ok": true,
      "iterations": 1
    },
    {
      "latency_seconds": 1.644251506004366,
      "status": "ok",
      "error": null,
      "agent_ok": true,
      "iterations": 1
    },
    {
      "latency_seconds": 0.6632501809945097,
      "status": "ok",
      "error": null,
      "agent_ok": true,
      "iterations": 1
    },
    {
      "latency_seconds": 3.6448539459961466,
      "status": "ok",
      "error": null,
      "agent_ok": false,
      "iterations": 1
    },
    {
      "latency_seconds": 0.8185894210037077,
      "status": "ok",
      "error": null,
      "agent_ok": true,
      "iterations": 1
    },
    {
      "latency_seconds": 1.1297246880130842,
      "status": "ok",
      "error": null,
      "agent_ok": true,
      "iterations": 1
    },
    {
      "latency_seconds": 0.6590888509963406,
      "status": "ok",
      "error": null,
      "agent_ok": true,
      "iterations": 1
    },
    {
      "latency_seconds": 0.9775046159920748,
      "status": "ok",
      "error": null,
      "agent_ok": true,
      "iterations": 1
    },
    {
      "latency_seconds": 3.7645545059931464,
      "status": "ok",
      "error": null,
      "agent_ok": true,
      "iterations": 1
    },
    {
      "latency_seconds": 0.9385306519980077,
      "status": "ok",
      "error": null,
      "agent_ok": true,
      "iterations": 1
    },
    {
      "latency_seconds": 1.5098030909866793,
      "status": "ok",
      "error": null,
      "agent_ok": true,
      "iterations": 1
    },
    {
      "latency_seconds": 2.0644392729882384,
      "status": "ok",
      "error": null,
      "agent_ok": true,
      "iterations": 1
    },
    {
      "latency_seconds": 0.9155671070038807,
      "status": "ok",
      "error": null,
      "agent_ok": true,
      "iterations": 1
    },
    {
      "latency_seconds": 0.908789163993788,
      "status": "ok",
      "error": null,
      "agent_ok": true,
      "iterations": 1
    },
    {
      "latency_seconds": 0.5735644670057809,
      "status": "ok",
      "error": null,
      "agent_ok": true,
      "iterations": 1
    },
    {
      "latency_seconds": 0.9959038919914747,
      "status": "ok",
      "error": null,
      "agent_ok": true,
      "iterations": 1
    },
    {
      "latency_seconds": 1.2828774939989671,
      "status": "ok",
      "error": null,
      "agent_ok": true,
      "iterations": 1
    },
    {
      "latency_seconds": 2.843690369001706,
      "status": "ok",
      "error": null,
      "agent_ok": true,
      "iterations": 1
    },
    {
      "latency_seconds": 1.2780149659956805,
      "status": "ok",
      "error": null,
      "agent_ok": true,
      "iterations": 1
    },
    {
      "latency_seconds": 0.8974137890036218,
      "status": "ok",
      "error": null,
      "agent_ok": true,
      "iterations": 1
    },
    {
      "latency_seconds": 0.7768401950015686,
      "status": "ok",
      "error": null,
      "agent_ok": true,
      "iterations": 1
    },
    {
      "latency_seconds": 1.455125455991947,
      "status": "ok",
      "error": null,
      "agent_ok": true,
      "iterations": 1
    },
    {
      "latency_seconds": 1.3590651150007034,
      "status": "ok",
      "error": null,
      "agent_ok": true,
      "iterations": 1
    },
    {
      "latency_seconds": 0.5183839149976848,
      "status": "ok",
      "error": null,
      "agent_ok": true,
      "iterations": 1
    },
    {
      "latency_seconds": 1.173967064009048,
      "status": "ok",
      "error": null,
      "agent_ok": true,
      "iterations": 1
    },
    {
      "latency_seconds": 4.443245036993176,
      "status": "ok",
      "error": null,
      "agent_ok": true,
      "iterations": 1
    },
    {
      "latency_seconds": 1.6717718370055081,
      "status": "ok",
      "error": null,
      "agent_ok": true,
      "iterations": 1
    },
    {
      "latency_seconds": 0.9574314579949714,
      "status": "ok",
      "error": null,
      "agent_ok": true,
      "iterations": 1
    },
    {
      "latency_seconds": 1.1689682599972002,
      "status": "ok",
      "error": null,
      "agent_ok": true,
      "iterations": 1
    },
    {
      "latency_seconds": 2.0474205589998746,
      "status": "ok",
      "error": null,
      "agent_ok": true,
      "iterations": 1
    },
    {
      "latency_seconds": 0.862374763994012,
      "status": "ok",
      "error": null,
      "agent_ok": true,
      "iterations": 1
    },
    {
      "latency_seconds": 3.821760752995033,
      "status": "ok",
      "error": null,
      "agent_ok": true,
      "iterations": 1
    },
    {
      "latency_seconds": 0.8742734219995327,
      "status": "ok",
      "error": null,
      "agent_ok": true,
      "iterations": 1
    },
    {
      "latency_seconds": 2.0180907160101924,
      "status": "ok",
      "error": null,
      "agent_ok": true,
      "iterations": 1
    },
    {
      "latency_seconds": 1.1923145990003832,
      "status": "ok",
      "error": null,
      "agent_ok": true,
      "iterations": 1
    },
    {
      "latency_seconds": 1.8896465489960974,
      "status": "ok",
      "error": null,
      "agent_ok": true,
      "iterations": 1
    },
    {
      "latency_seconds": 1.18605647199729,
      "status": "ok",
      "error": null,
      "agent_ok": true,
      "iterations": 1
    },
    {
      "latency_seconds": 4.626607508005691,
      "status": "ok",
      "error": null,
      "agent_ok": true,
      "iterations": 1
    },
    {
      "latency_seconds": 1.900097140998696,
      "status": "ok",
      "error": null,
      "agent_ok": false,
      "iterations": 1
    },
    {
      "latency_seconds": 1.5457528719998663,
      "status": "ok",
      "error": null,
      "agent_ok": true,
      "iterations": 1
    },
    {
      "latency_seconds": 0.7874754759977804,
      "status": "ok",
      "error": null,
      "agent_ok": true,
      "iterations": 1
    },
    {
      "latency_seconds": 1.3423102530068718,
      "status": "ok",
      "error": null,
      "agent_ok": true,
      "iterations": 1
    },
    {
      "latency_seconds": 2.8813587999902666,
      "status": "ok",
      "error": null,
      "agent_ok": true,
      "iterations": 1
    },
    {
      "latency_seconds": 1.0891491289949045,
      "status": "ok",
      "error": null,
      "agent_ok": true,
      "iterations": 1
    },
    {
      "latency_seconds": 3.56625680300931,
      "status": "ok",
      "error": null,
      "agent_ok": true,
      "iterations": 1
    },
    {
      "latency_seconds": 0.5172270240000216,
      "status": "ok",
      "error": null,
      "agent_ok": true,
      "iterations": 1
    },
    {
      "latency_seconds": 1.0128185969952028,
      "status": "ok",
      "error": null,
      "agent_ok": true,
      "iterations": 1
    },
    {
      "latency_seconds": 4.883052867997321,
      "status": "ok",
      "error": null,
      "agent_ok": true,
      "iterations": 1
    },
    {
      "latency_seconds": 1.0802013200009242,
      "status": "ok",
      "error": null,
      "agent_ok": true,
      "iterations": 1
    },
    {
      "latency_seconds": 1.5634943710028892,
      "status": "ok",
      "error": null,
      "agent_ok": true,
      "iterations": 1
    },
    {
      "latency_seconds": 0.9949097889912082,
      "status": "ok",
      "error": null,
      "agent_ok": true,
      "iterations": 1
    },
    {
      "latency_seconds": 3.083638849988347,
      "status": "ok",
      "error": null,
      "agent_ok": true,
      "iterations": 1
    },
    {
      "latency_seconds": 1.2591373009927338,
      "status": "ok",
      "error": null,
      "agent_ok": true,
      "iterations": 1
    },
    {
      "latency_seconds": 3.839059018995613,
      "status": "ok",
      "error": null,
      "agent_ok": true,
      "iterations": 1
    },
    {
      "latency_seconds": 1.4674514110083692,
      "status": "ok",
      "error": null,
      "agent_ok": true,
      "iterations": 1
    },
    {
      "latency_seconds": 7.20457338799315,
      "status": "ok",
      "error": null,
      "agent_ok": true,
      "iterations": 1
    },
    {
      "latency_seconds": 1.0223269600101048,
      "status": "ok",
      "error": null,
      "agent_ok": true,
      "iterations": 1
    },
    {
      "latency_seconds": 5.043812595002237,
      "status": "ok",
      "error": null,
      "agent_ok": true,
      "iterations": 1
    },
    {
      "latency_seconds": 4.772910012005013,
      "status": "ok",
      "error": null,
      "agent_ok": true,
      "iterations": 1
    },
    {
      "latency_seconds": 3.5138296479999553,
      "status": "ok",
      "error": null,
      "agent_ok": true,
      "iterations": 1
    }
  ]
}